bro/__init__.py
bro/__version__.py
bro/api.py
bro/helper_functions.py
bro/objects.py
examples/__init__.py
examples/examples.py
bro-0.2.11.dist-info/LICENSE.txt
bro-0.2.11.dist-info/METADATA
bro-0.2.11.dist-info/WHEEL
bro-0.2.11.dist-info/top_level.txt
bro-0.2.11.dist-info/RECORD
