Metadata-Version: 2.1
Name: bro
Version: 0.2.11
Summary: Open source python library for accessing BRO API
Author: VIKTOR
Author-email: support@viktor.ai
License: see LICENSE.txt
Project-URL: Source code, https://github.com/viktor-platform/bro
Project-URL: Example VIKTOR application, https://demo.viktor.ai/public/bro-app
Project-URL: Source code VIKTOR application, https://github.com/viktor-platform/bro-app
Classifier: Environment :: Web Environment
Classifier: Intended Audience :: Developers
Classifier: License :: OSI Approved :: MIT License
Classifier: Operating System :: Microsoft :: Windows
Classifier: Operating System :: POSIX :: Linux
Classifier: Programming Language :: Python :: 3.8
Classifier: Programming Language :: Python :: 3.9
Classifier: Programming Language :: Python :: 3.10
Classifier: Programming Language :: Python :: 3.11
License-File: LICENSE.txt
Requires-Dist: xmltodict >=0.13.0
Requires-Dist: requests >=2.31.0
Requires-Dist: lxml >=5.1.0
Requires-Dist: pyproj >=3.6.1
